typer_util/__init__.py
typer_util/__version__.py
typer_util/exit.py
typer_util/logging.py
typer_util/settings.py
typer_util/types.py
typer_util-0.0.1.dist-info/METADATA
typer_util-0.0.1.dist-info/WHEEL
typer_util-0.0.1.dist-info/licenses/LICENSE
typer_util-0.0.1.dist-info/RECORD
