Metadata-Version: 2.1
Name: typer_util
Version: 0.0.1
Summary: Utilities for enriching the Typer CLI experience
Project-URL: Changelog, https://github.com/hyprxa/typer_util/blob/master/CHANGELOG.md
Project-URL: Homepage, https://github.com/hyprxa/typer_util
Project-URL: Source, https://github.com/hyprxa/typer_util
Author-email: Chris Newville <christopher.newville@hyprxa.io>
License-Expression: MIT
License-File: LICENSE
Classifier: Development Status :: 3 - Alpha
Classifier: Intended Audience :: Developers
Classifier: License :: OSI Approved :: MIT License
Classifier: Operating System :: OS Independent
Classifier: Programming Language :: Python :: 3
Classifier: Programming Language :: Python :: 3 :: Only
Classifier: Programming Language :: Python :: 3.8
Classifier: Programming Language :: Python :: 3.9
Classifier: Programming Language :: Python :: 3.10
Classifier: Programming Language :: Python :: 3.11
Classifier: Programming Language :: Python :: 3.12
Requires-Python: <4.0,>=3.8
Requires-Dist: click
Requires-Dist: pydantic
Requires-Dist: pydantic-settings
Requires-Dist: rich
Requires-Dist: typer
Provides-Extra: kerberos
Requires-Dist: httpx-kerberos; extra == 'kerberos'
